{
  "events": [
    {
      "address": "5519 Leigh Run Ct. Columbus, OH 43228",
      "coord_x": 39.9355845,
      "coord_y": -83.1423885,
      "count": 1,
      "date": "1/1/2019",
      "incident": "190001041",
      "source": "https://www.columbus.gov/WorkArea/DownloadAsset.aspx?id=2147507993",
      "year": 2019
    },
    {
      "address": "2327 Ontario St. Columbus, OH 43211",
      "coord_x": 40.0135665,
      "coord_y": -82.9771421,
      "count": 2,
      "date": "1/29/2019",
      "incident": "190079413",
      "source": "https://www.columbus.gov/WorkArea/DownloadAsset.aspx?id=2147508411",
      "year": 2019
    },
    {
      "address": "3655 Sullivant Ave. Columbus, OH 43228",
      "coord_x": 39.9418635,
      "coord_y": -83.0963798,
      "count": 3,
      "date": "1/29/2019",
      "incident": "190078564",
      "source": "https://www.columbus.gov/WorkArea/DownloadAsset.aspx?id=2147508372",
      "year": 2019
    },
    {
      "address": "6424 Alder Ct. Columbus, OH 43235",
      "coord_x": 40.0897,
      "coord_y": -83.05548999999999,
      "count": 4,
      "date": "1/28/2019",
      "incident": "190076827",
      "source": "https://www.columbus.gov/WorkArea/DownloadAsset.aspx?id=2147508395",
      "year": 2019
    },
    {
      "address": "3439 E. Broad St. Columbus, OH 43213",
      "coord_x": 39.972053,
      "coord_y": -82.90878339999999,
      "count": 5,
      "date": "1/20/2019",
      "incident": "190052362",
      "source": "https://www.columbus.gov/WorkArea/DownloadAsset.aspx?id=2147508239",
      "year": 2019
    },
    {
      "address": "7208 Billy Goat Dr. New Albany, OH 43054",
      "coord_x": 40.10502839999999,
      "coord_y": -82.82311600000001,
      "count": 6,
      "date": "1/18/2019",
      "incident": "190047902",
      "source": "https://www.columbus.gov/WorkArea/DownloadAsset.aspx?id=2147508268",
      "year": 2019
    },
    {
      "address": "1044 Loretta Ave. Columbus, OH 43211",
      "coord_x": 40.0154799,
      "coord_y": -82.982429,
      "count": 7,
      "date": "1/11/2019",
      "incident": "190029588",
      "source": "https://www.columbus.gov/WorkArea/DownloadAsset.aspx?id=2147508148",
      "year": 2019
    },
    {
      "address": "3749 Noam Ct. Columbus, OH 43232",
      "coord_x": 39.9226864,
      "coord_y": -82.8970951,
      "count": 8,
      "date": "1/11/2019",
      "incident": "190028034",
      "source": "https://www.columbus.gov/WorkArea/DownloadAsset.aspx?id=2147508147",
      "year": 2019
    },
    {
      "address": "1042 Lockbourne Rd. Columbus, OH 43206",
      "coord_x": 39.9446767,
      "coord_y": -82.9634129,
      "count": 9,
      "date": "1/8/2019",
      "incident": "190021560",
      "source": "https://www.columbus.gov/WorkArea/DownloadAsset.aspx?id=2147508070",
      "year": 2019
    },
    {
      "address": "3471 Kimberly Ave. Columbus, OH 43224",
      "coord_x": 40.0358852,
      "coord_y": -82.9923917,
      "count": 10,
      "date": "1/7/2019",
      "incident": "190018639",
      "source": "https://www.columbus.gov/WorkArea/DownloadAsset.aspx?id=2147508065",
      "year": 2019
    },
    {
      "address": "50 Wisconsin Ave. Columbus, OH 43222",
      "coord_x": 39.9594246,
      "coord_y": -83.03292239999999,
      "count": 11,
      "date": "2/27/2019",
      "incident": "180284087",
      "source": "https://www.columbus.gov/WorkArea/DownloadAsset.aspx?id=2147508843",
      "year": 2019
    },
    {
      "address": "2065 W. Mound St. Columbus, OH 43223",
      "coord_x": 39.9409869,
      "coord_y": -83.0529121,
      "count": 12,
      "date": "2/25/2019",
      "incident": "190155596",
      "source": "https://www.columbus.gov/WorkArea/DownloadAsset.aspx?id=2147508808",
      "year": 2019
    },
    {
      "address": "969 Seymour Ave. Columbus, OH 43206",
      "coord_x": 39.94706860000001,
      "coord_y": -82.95516529999999,
      "count": 13,
      "date": "2/24/2019",
      "incident": "190150914",
      "source": "https://www.columbus.gov/WorkArea/DownloadAsset.aspx?id=2147508803",
      "year": 2019
    },
    {
      "address": "3162 E. 13th Ave. Columbus, OH 43219",
      "coord_x": 39.9921701,
      "coord_y": -82.9205947,
      "count": 14,
      "date": "2/23/2019",
      "incident": "190147613",
      "source": "https://www.columbus.gov/WorkArea/DownloadAsset.aspx?id=2147508765",
      "year": 2019
    },
    {
      "address": "362 Loeffler Ave. Columbus, OH 43205",
      "coord_x": 39.9590104,
      "coord_y": -82.96162369999999,
      "count": 15,
      "date": "2/19/2019",
      "incident": "190119196",
      "source": "https://www.columbus.gov/WorkArea/DownloadAsset.aspx?id=2147508622",
      "year": 2019
    },
    {
      "address": "2140 Schenley Dr. Columbus, OH 43219",
      "coord_x": 40.0051548,
      "coord_y": -82.950975,
      "count": 16,
      "date": "2/10/2019",
      "incident": "190113264",
      "source": "https://www.columbus.gov/WorkArea/DownloadAsset.aspx?id=2147508492",
      "year": 2019
    },
    {
      "address": "2447 E. Dublin-Granville Rd. Columbus, OH 43229",
      "coord_x": 40.0853435,
      "coord_y": -82.9543439,
      "count": 17,
      "date": "3/29/2019",
      "incident": "171005027",
      "source": "https://www.columbus.gov/WorkArea/DownloadAsset.aspx?id=2147509597",
      "year": 2019
    },
    {
      "address": "1161 E. 21st Ave. Columbus, OH 43211",
      "coord_x": 40.0039152,
      "coord_y": -82.9771841,
      "count": 18,
      "date": "3/25/2019",
      "incident": "190179709",
      "source": "https://www.columbus.gov/WorkArea/DownloadAsset.aspx?id=2147509495",
      "year": 2019
    },
    {
      "address": "2174 Winslow Dr. Columbus, OH 43207",
      "coord_x": 39.9252678,
      "coord_y": -82.9376041,
      "count": 19,
      "date": "3/25/2019",
      "incident": "190232697",
      "source": "https://www.columbus.gov/WorkArea/DownloadAsset.aspx?id=2147509671",
      "year": 2019
    },
    {
      "address": "3216 Balsam Lake Dr. Columbus, OH 43219",
      "coord_x": 40.0279151,
      "coord_y": -82.9192343,
      "count": 20,
      "date": "3/24/2019",
      "incident": "190230703",
      "source": "https://www.columbus.gov/WorkArea/DownloadAsset.aspx?id=2147509509",
      "year": 2019
    },
    {
      "address": "33 E. Duncan St. Columbus, OH 43202",
      "coord_x": 40.0155354,
      "coord_y": -83.0106654,
      "count": 21,
      "date": "3/24/2019",
      "incident": "190230020",
      "source": "https://www.columbus.gov/WorkArea/DownloadAsset.aspx?id=2147509494",
      "year": 2019
    },
    {
      "address": "140 Columbian Ave. Columbus, OH 43223",
      "coord_x": 39.9532627,
      "coord_y": -83.04991869999999,
      "count": 22,
      "date": "3/21/2019",
      "incident": "190221969",
      "source": "https://www.columbus.gov/WorkArea/DownloadAsset.aspx?id=2147509508",
      "year": 2019
    },
    {
      "address": "1300 S. Columbus Airport Rd. Columbus, OH 43207",
      "coord_x": 39.8833038,
      "coord_y": -82.96678659999999,
      "count": 23,
      "date": "3/20/2019",
      "incident": "170252675",
      "source": "https://www.columbus.gov/WorkArea/DownloadAsset.aspx?id=2147509311",
      "year": 2019
    },
    {
      "address": "4098 Raft Ln. Columbus, OH 43207",
      "coord_x": 39.8844269,
      "coord_y": -82.9185557,
      "count": 24,
      "date": "3/15/2019",
      "incident": "190205344",
      "source": "https://www.columbus.gov/WorkArea/DownloadAsset.aspx?id=2147509245",
      "year": 2019
    },
    {
      "address": "1047 Atcheson St. Columbus, OH 43203",
      "coord_x": 39.9733354,
      "coord_y": -82.9743591,
      "count": 25,
      "date": "3/13/2019",
      "incident": "100436283",
      "source": "https://www.columbus.gov/WorkArea/DownloadAsset.aspx?id=2147509200",
      "year": 2019
    },
    {
      "address": "1329 Aberdeen Ave. Columbus, OH 43211",
      "coord_x": 40.0209835,
      "coord_y": -82.9757983,
      "count": 26,
      "date": "3/10/2019",
      "incident": "190190844",
      "source": "https://www.columbus.gov/WorkArea/DownloadAsset.aspx?id=2147509167",
      "year": 2019
    },
    {
      "address": "427 S. Champion Ave. Columbus, OH 43205",
      "coord_x": 39.9567811,
      "coord_y": -82.96978229999999,
      "count": 27,
      "date": "3/5/2019",
      "incident": "190073906",
      "source": "https://www.columbus.gov/WorkArea/DownloadAsset.aspx?id=2147509037",
      "year": 2019
    },
    {
      "address": "555 S. Eureka Ave. Columbus, OH 43204",
      "coord_x": 39.9437943,
      "coord_y": -83.06451469999999,
      "count": 28,
      "date": "3/2/2019",
      "incident": "190169448",
      "source": "https://www.columbus.gov/WorkArea/DownloadAsset.aspx?id=2147509290",
      "year": 2019
    },
    {
      "address": "604 Whitethorne Ave. Columbus, OH 43223",
      "coord_x": 39.9433137,
      "coord_y": -83.0551619,
      "count": 29,
      "date": "4/28/2019",
      "incident": "190333648",
      "source": "https://www.columbus.gov/WorkArea/DownloadAsset.aspx?id=2147510056",
      "year": 2019
    },
    {
      "address": "925 W. Town St. Columbus, OH 43222",
      "coord_x": 39.955444,
      "coord_y": -83.024654,
      "count": 30,
      "date": "4/25/2019",
      "incident": "190327315",
      "source": "https://www.columbus.gov/WorkArea/DownloadAsset.aspx?id=2147510011",
      "year": 2019
    },
    {
      "address": "231 S. Harris Ave. Columbus, OH 43204",
      "coord_x": 39.95016,
      "coord_y": -83.07261869999999,
      "count": 31,
      "date": "4/25/2019",
      "incident": "190322124",
      "source": "https://www.columbus.gov/WorkArea/DownloadAsset.aspx?id=2147510008",
      "year": 2019
    },
    {
      "address": "3951 E. Livingston Ave. Columbus, OH 43227",
      "coord_x": 39.9449993,
      "coord_y": -82.8904319,
      "count": 32,
      "date": "4/22/2019",
      "incident": "190318230",
      "source": "https://www.columbus.gov/WorkArea/DownloadAsset.aspx?id=2147509990",
      "year": 2019
    },
    {
      "address": "121 Niles Dr. Columbus, OH 43207",
      "coord_x": 39.8931008,
      "coord_y": -82.9995442,
      "count": 33,
      "date": "4/22/2019",
      "incident": "190317427",
      "source": "https://www.columbus.gov/WorkArea/DownloadAsset.aspx?id=2147509966",
      "year": 2019
    },
    {
      "address": "S. 22nd St. & E. Rich St. (Area of)",
      "coord_x": 27.752088,
      "coord_y": -82.6635,
      "count": 34,
      "date": "4/16/2019",
      "incident": "190300225",
      "source": "https://www.columbus.gov/WorkArea/DownloadAsset.aspx?id=2147509989",
      "year": 2019
    },
    {
      "address": "1399 S. Hamilton Rd. Columbus, OH 43227",
      "coord_x": 39.9463148,
      "coord_y": -82.8782576,
      "count": 35,
      "date": "4/14/2019",
      "incident": "190291998",
      "source": "https://www.columbus.gov/WorkArea/DownloadAsset.aspx?id=2147510000",
      "year": 2019
    },
    {
      "address": "1765 S. 8th St. Columbus, OH 43207",
      "coord_x": 39.926729,
      "coord_y": -82.9883464,
      "count": 36,
      "date": "4/11/2019",
      "incident": "190284346",
      "source": "https://www.columbus.gov/WorkArea/DownloadAsset.aspx?id=2147509807",
      "year": 2019
    },
    {
      "address": "1506 Marsdale Ave. Columbus, OH 43223",
      "coord_x": 39.919131,
      "coord_y": -83.04205,
      "count": 37,
      "date": "5/31/2019",
      "incident": "190439951",
      "source": "https://www.columbus.gov/WorkArea/DownloadAsset.aspx?id=2147510453",
      "year": 2019
    },
    {
      "address": "2223 Hamilton Ave. Columbus, OH 43211",
      "coord_x": 40.011191,
      "coord_y": -82.97940969999999,
      "count": 38,
      "date": "5/24/2019",
      "incident": "190415796",
      "source": "https://www.columbus.gov/WorkArea/DownloadAsset.aspx?id=2147510423",
      "year": 2019
    },
    {
      "address": "1444 Shady Ln. Columbus, OH 43227",
      "coord_x": 39.9457276,
      "coord_y": -82.8704559,
      "count": 39,
      "date": "5/22/2019",
      "incident": "190410356",
      "source": "https://www.columbus.gov/WorkArea/DownloadAsset.aspx?id=2147510429",
      "year": 2019
    },
    {
      "address": "770 Kerr St. Columbus, OH 43215",
      "coord_x": 39.9783195,
      "coord_y": -83.0016157,
      "count": 40,
      "date": "5/21/2019",
      "incident": "190405087",
      "source": "https://www.columbus.gov/WorkArea/DownloadAsset.aspx?id=2147510340",
      "year": 2019
    },
    {
      "address": "6091 McNaughten Center, Columbus OH 43232",
      "coord_x": 39.9530763,
      "coord_y": -82.8378297,
      "count": 41,
      "date": "5/14/2019",
      "incident": "190383026",
      "source": "https://www.columbus.gov/WorkArea/DownloadAsset.aspx?id=2147510262",
      "year": 2019
    },
    {
      "address": "966 E. 19th Ave. Columbus, OH 43211",
      "coord_x": 40.0029042,
      "coord_y": -82.9822231,
      "count": 42,
      "date": "5/13/2019",
      "incident": "190382148",
      "source": "https://www.columbus.gov/WorkArea/DownloadAsset.aspx?id=2147510281",
      "year": 2019
    },
    {
      "address": "60 Cotterrew Dr. Blacklick, OH 43004",
      "coord_x": 39.9844406,
      "coord_y": -82.8067507,
      "count": 43,
      "date": "5/9/2019",
      "incident": "190369336",
      "source": "https://www.columbus.gov/WorkArea/DownloadAsset.aspx?id=2147510210",
      "year": 2019
    },
    {
      "address": "807 Fairwood Ave. Columbus, OH 43205",
      "coord_x": 39.9505449,
      "coord_y": -82.9537266,
      "count": 44,
      "date": "5/8/2019",
      "incident": "190365054",
      "source": "https://www.columbus.gov/WorkArea/DownloadAsset.aspx?id=2147510188",
      "year": 2019
    },
    {
      "address": "1331 Gault St. Columbus, OH 43205",
      "coord_x": 39.9505333,
      "coord_y": -82.96240069999999,
      "count": 45,
      "date": "5/5/2019",
      "incident": "190356061",
      "source": "https://www.columbus.gov/WorkArea/DownloadAsset.aspx?id=2147510141",
      "year": 2019
    },
    {
      "address": "1311 E. 23rd Ave. Columbus, OH 43211",
      "coord_x": 40.005487,
      "coord_y": -82.9733325,
      "count": 46,
      "date": "5/2/2019",
      "incident": "190346318",
      "source": "https://www.columbus.gov/WorkArea/DownloadAsset.aspx?id=2147510111",
      "year": 2019
    },
    {
      "address": "312 Stanaford Pl. Columbus, OH 43207",
      "coord_x": 39.9265486,
      "coord_y": -82.9871824,
      "count": 47,
      "date": "6/29/2019",
      "incident": "190533327",
      "source": "https://www.columbus.gov/WorkArea/DownloadAsset.aspx?id=2147510793",
      "year": 2019
    },
    {
      "address": "3853 Sullivant Ave. Columbus, OH 43228",
      "coord_x": 39.9414654,
      "coord_y": -83.1014307,
      "count": 48,
      "date": "6/29/2019",
      "incident": "190531213",
      "source": "https://www.columbus.gov/WorkArea/DownloadAsset.aspx?id=2147510854",
      "year": 2019
    },
    {
      "address": "1156 Pauline Ave. Columbus, OH 43224",
      "coord_x": 40.038351,
      "coord_y": -82.9840287,
      "count": 49,
      "date": "6/27/2019",
      "incident": "190525587",
      "source": "https://www.columbus.gov/WorkArea/DownloadAsset.aspx?id=2147510779",
      "year": 2019
    },
    {
      "address": "4638 Tamarack Blvd. Columbus, OH 43229",
      "coord_x": 40.0628463,
      "coord_y": -82.9707284,
      "count": 50,
      "date": "6/10/2019",
      "incident": "190472535",
      "source": "https://www.columbus.gov/WorkArea/DownloadAsset.aspx?id=2147510547",
      "year": 2019
    },
    {
      "address": "40 W. Welch Ave. Columbus, OH 43207",
      "coord_x": 39.9307395,
      "coord_y": -82.99701689999999,
      "count": 51,
      "date": "6/6/2019",
      "incident": "190456435",
      "source": "https://www.columbus.gov/WorkArea/DownloadAsset.aspx?id=2147510474",
      "year": 2019
    },
    {
      "address": "834 Greenfield Dr. Columbus, OH 43223",
      "coord_x": 39.9425669,
      "coord_y": -83.0198147,
      "count": 52,
      "date": "6/3/2019",
      "incident": "190447643",
      "source": "https://www.columbus.gov/WorkArea/DownloadAsset.aspx?id=2147510441",
      "year": 2019
    },
    {
      "address": "35 W. 5th Ave. Columbus, OH 43201",
      "coord_x": 39.9870178,
      "coord_y": -83.006531,
      "count": 53,
      "date": "6/2/2019",
      "incident": "190444093",
      "source": "https://www.columbus.gov/WorkArea/DownloadAsset.aspx?id=2147510439",
      "year": 2019
    },
    {
      "address": "310 Stanaford Pl. Columbus, OH 43207",
      "coord_x": 39.9265259,
      "coord_y": -82.9872527,
      "count": 54,
      "date": "6/1/2019",
      "incident": "190442752",
      "source": "https://www.columbus.gov/WorkArea/DownloadAsset.aspx?id=2147510438",
      "year": 2019
    },
    {
      "address": "6731 Lagrange Dr. Canal Winchester, OH 43110",
      "coord_x": 39.87420669999999,
      "coord_y": -82.8228577,
      "count": 55,
      "date": "7/31/2019",
      "incident": "190634676",
      "source": "https://www.columbus.gov/WorkArea/DownloadAsset.aspx?id=2147511284",
      "year": 2019
    },
    {
      "address": "826 Wedgewood Dr. Columbus, OH 43228",
      "coord_x": 39.9369069,
      "coord_y": -83.0970308,
      "count": 56,
      "date": "7/30/2019",
      "incident": "181081371",
      "source": "https://www.columbus.gov/WorkArea/DownloadAsset.aspx?id=2147511266",
      "year": 2019
    },
    {
      "address": "898 Weldon Ave. Columbus, OH 43224",
      "coord_x": 40.0283361,
      "coord_y": -82.9891931,
      "count": 57,
      "date": "7/26/2019",
      "incident": "190619759",
      "source": "https://www.columbus.gov/WorkArea/DownloadAsset.aspx?id=2147511233",
      "year": 2019
    },
    {
      "address": "1113 Oakwood Ave. Columbus, OH 43206",
      "coord_x": 39.942523,
      "coord_y": -82.969692,
      "count": 58,
      "date": "7/24/2019",
      "incident": "190611028",
      "source": "https://www.columbus.gov/WorkArea/DownloadAsset.aspx?id=2147511188",
      "year": 2019
    },
    {
      "address": "1667 Genessee Ave. Columbus, OH 43211",
      "coord_x": 40.018424,
      "coord_y": -82.966076,
      "count": 59,
      "date": "7/12/2019",
      "incident": "190573405",
      "source": "https://www.columbus.gov/WorkArea/DownloadAsset.aspx?id=2147510923",
      "year": 2019
    },
    {
      "address": "4436 Westerville Rd. Columbus, OH 43231",
      "coord_x": 40.061954,
      "coord_y": -82.9342793,
      "count": 60,
      "date": "7/12/2019",
      "incident": "180946032",
      "source": "https://www.columbus.gov/WorkArea/DownloadAsset.aspx?id=2147510922",
      "year": 2019
    },
    {
      "address": "5440 E. Livingston Ave. Columbus, OH 43232",
      "coord_x": 39.94371390000001,
      "coord_y": -82.84957779999999,
      "count": 61,
      "date": "7/11/2019",
      "incident": "190571831",
      "source": "https://www.columbus.gov/WorkArea/DownloadAsset.aspx?id=2147510927",
      "year": 2019
    },
    {
      "address": "3087 Sun Valley Dr. Pickerington, OH 43147",
      "coord_x": 39.9215322,
      "coord_y": -82.7979246,
      "count": 62,
      "date": "7/9/2019",
      "incident": "190059143",
      "source": "https://www.columbus.gov/WorkArea/DownloadAsset.aspx?id=2147510897",
      "year": 2019
    },
    {
      "address": "3566 Odonnell Ct. Columbus, OH 43228",
      "coord_x": 39.9259738,
      "coord_y": -83.091538,
      "count": 63,
      "date": "7/8/2019",
      "incident": "190560511",
      "source": "https://www.columbus.gov/WorkArea/DownloadAsset.aspx?id=2147510882",
      "year": 2019
    },
    {
      "address": "82 S. Richardson Ave. Columbus, OH 43204",
      "coord_x": 39.9534499,
      "coord_y": -83.06770190000002,
      "count": 64,
      "date": "7/7/2019",
      "incident": "190559893",
      "source": "https://www.columbus.gov/WorkArea/DownloadAsset.aspx?id=2147510884",
      "year": 2019
    },
    {
      "address": "3605 Cushing Dr. Columbus, OH 43227",
      "coord_x": 39.9439625,
      "coord_y": -82.8992404,
      "count": 65,
      "date": "8/30/2019",
      "incident": "190731112",
      "source": "https://www.columbus.gov/WorkArea/DownloadAsset.aspx?id=2147511590",
      "year": 2019
    },
    {
      "address": "2971 E. Moreland Dr. Columbus, OH 43209",
      "coord_x": 39.95004489999999,
      "coord_y": -82.9178284,
      "count": 66,
      "date": "8/29/2019",
      "incident": "190726466",
      "source": "https://www.columbus.gov/WorkArea/DownloadAsset.aspx?id=2147511573",
      "year": 2019
    },
    {
      "address": "925 Mt. Vernon Ave. Columbus, OH 43203",
      "coord_x": 39.9711659,
      "coord_y": -82.97725899999999,
      "count": 67,
      "date": "8/28/2019",
      "incident": "190721178",
      "source": "https://www.columbus.gov/WorkArea/DownloadAsset.aspx?id=2147511553",
      "year": 2019
    },
    {
      "address": "154 N. Central Ave. Columbus, OH 43222",
      "coord_x": 39.9609252,
      "coord_y": -83.03855,
      "count": 68,
      "date": "8/24/2019",
      "incident": "180406259",
      "source": "https://www.columbus.gov/WorkArea/DownloadAsset.aspx?id=2147511509",
      "year": 2019
    },
    {
      "address": "1713 E. Columbus St. Columbus, OH 43206",
      "coord_x": 39.9442854,
      "coord_y": -82.9509329,
      "count": 69,
      "date": "8/23/2019",
      "incident": "190708821",
      "source": "https://www.columbus.gov/WorkArea/DownloadAsset.aspx?id=2147511510",
      "year": 2019
    },
    {
      "address": "382 Stoddart Ave. Columbus, OH 43205",
      "coord_x": 39.959345,
      "coord_y": -82.95355599999999,
      "count": 70,
      "date": "8/13/2019",
      "incident": "190673829",
      "source": "https://www.columbus.gov/WorkArea/DownloadAsset.aspx?id=2147511399",
      "year": 2019
    },
    {
      "address": "2677 Jonathan Park Way, Reynoldsburg, OH 43068",
      "coord_x": 39.92934,
      "coord_y": -82.8018549,
      "count": 71,
      "date": "8/9/2019",
      "incident": "190694994",
      "source": "https://www.columbus.gov/WorkArea/DownloadAsset.aspx?id=2147511382",
      "year": 2019
    },
    {
      "address": "1175 Lenore Ave. Columbus, OH 43224",
      "coord_x": 40.0359323,
      "coord_y": -82.9829369,
      "count": 72,
      "date": "8/8/2019",
      "incident": "190691423",
      "source": "https://www.columbus.gov/WorkArea/DownloadAsset.aspx?id=2147511424",
      "year": 2019
    },
    {
      "address": "1323 Republic Ave. Columbus, OH 43211",
      "coord_x": 40.0156677,
      "coord_y": -82.97495839999999,
      "count": 73,
      "date": "8/1/2019",
      "incident": "190636474",
      "source": "https://www.columbus.gov/WorkArea/DownloadAsset.aspx?id=2147511286",
      "year": 2019
    },
    {
      "address": "1584 Zettler Rd. Columbus, OH 43227",
      "coord_x": 39.9388807,
      "coord_y": -82.9108012,
      "count": 74,
      "date": "9/30/2019",
      "incident": "190828863",
      "source": "https://www.columbus.gov/WorkArea/DownloadAsset.aspx?id=2147511965",
      "year": 2019
    },
    {
      "address": "950 Mt. Vernon Ave. Columbus, OH 43203",
      "coord_x": 39.9716556,
      "coord_y": -82.9767509,
      "count": 75,
      "date": "9/30/2019",
      "incident": "190827317",
      "source": "https://www.columbus.gov/WorkArea/DownloadAsset.aspx?id=2147511947",
      "year": 2019
    },
    {
      "address": "145 S. Harris Ave. Columbus, OH 43204",
      "coord_x": 39.9519141,
      "coord_y": -83.07273409999999,
      "count": 76,
      "date": "9/27/2019",
      "incident": "190820101",
      "source": "https://www.columbus.gov/WorkArea/DownloadAsset.aspx?id=2147511936",
      "year": 2019
    },
    {
      "address": "2520 S. Hamilton Rd. Columbus, OH 43232",
      "coord_x": 39.9251225,
      "coord_y": -82.8789096,
      "count": 77,
      "date": "9/25/2019",
      "incident": "190811094",
      "source": "https://www.columbus.gov/WorkArea/DownloadAsset.aspx?id=2147511882",
      "year": 2019
    },
    {
      "address": "973 Moon Rd. Columbus, OH 43224",
      "coord_x": 40.0392552,
      "coord_y": -82.98973889999999,
      "count": 78,
      "date": "9/24/2019",
      "incident": "190810669",
      "source": "https://www.columbus.gov/WorkArea/DownloadAsset.aspx?id=2147511880",
      "year": 2019
    },
    {
      "address": "857 Moon Rd. Columbus, OH 43224",
      "coord_x": 40.0394698,
      "coord_y": -82.99251160000001,
      "count": 79,
      "date": "9/19/2019",
      "incident": "190795455",
      "source": "https://www.columbus.gov/WorkArea/DownloadAsset.aspx?id=2147511844",
      "year": 2019
    },
    {
      "address": "229 W. 9th Ave. Columbus, OH 43201",
      "coord_x": 39.992895,
      "coord_y": -83.012585,
      "count": 80,
      "date": "9/19/2019",
      "incident": "190795111",
      "source": "https://www.columbus.gov/WorkArea/DownloadAsset.aspx?id=2147511825",
      "year": 2019
    },
    {
      "address": "4453 Drifton Dr. Columbus, OH 43227",
      "coord_x": 39.9390615,
      "coord_y": -82.8753558,
      "count": 81,
      "date": "9/13/2019",
      "incident": "190775123",
      "source": "https://www.columbus.gov/WorkArea/DownloadAsset.aspx?id=2147511767",
      "year": 2019
    },
    {
      "address": "1275 E. 17th Ave. Columbus, OH 43211",
      "coord_x": 40.0000078,
      "coord_y": -82.9732786,
      "count": 82,
      "date": "9/10/2019",
      "incident": "190765735",
      "source": "https://www.columbus.gov/WorkArea/DownloadAsset.aspx?id=2147511758",
      "year": 2019
    },
    {
      "address": "2210 Ruskin Ave. Columbus, OH 43219",
      "coord_x": 39.9903328,
      "coord_y": -82.9460596,
      "count": 83,
      "date": "9/4/2019",
      "incident": "190743982",
      "source": "https://www.columbus.gov/WorkArea/DownloadAsset.aspx?id=2147511635",
      "year": 2019
    },
    {
      "address": "1317 E. 23rd Ave. Columbus, OH 43211",
      "coord_x": 40.0053937,
      "coord_y": -82.9732786,
      "count": 84,
      "date": "10/31/2019",
      "incident": "190918310",
      "source": "https://www.columbus.gov/WorkArea/DownloadAsset.aspx?id=2147512282",
      "year": 2019
    },
    {
      "address": "5593 Chatterton Rd. Columbus, OH 43232",
      "coord_x": 39.9129187,
      "coord_y": -82.846216,
      "count": 85,
      "date": "10/19/2019",
      "incident": "190884782",
      "source": "https://www.columbus.gov/WorkArea/DownloadAsset.aspx?id=2147512182",
      "year": 2019
    },
    {
      "address": "1141 E. 13th Ave. Columbus, OH 43201",
      "coord_x": 39.9964332,
      "coord_y": -82.9761762,
      "count": 86,
      "date": "10/16/2019",
      "incident": "190877061",
      "source": "https://www.columbus.gov/WorkArea/DownloadAsset.aspx?id=2147512155",
      "year": 2019
    },
    {
      "address": "1131 Fassett Ave. Columbus, OH 43201",
      "coord_x": 39.9886781,
      "coord_y": -82.9761704,
      "count": 87,
      "date": "10/15/2019",
      "incident": "190872703",
      "source": "https://www.columbus.gov/WorkArea/DownloadAsset.aspx?id=2147512154",
      "year": 2019
    },
    {
      "address": "1248 Brookway Rd. Columbus, OH 43227",
      "coord_x": 39.9473165,
      "coord_y": -82.8979371,
      "count": 88,
      "date": "10/12/2019",
      "incident": "190863438",
      "source": "https://www.columbus.gov/WorkArea/DownloadAsset.aspx?id=2147512113",
      "year": 2019
    },
    {
      "address": "1053 Rosewind Dr. Columbus, OH 43211",
      "coord_x": 39.9941598,
      "coord_y": -82.977386,
      "count": 89,
      "date": "10/11/2019",
      "incident": "190862828",
      "source": "https://www.columbus.gov/WorkArea/DownloadAsset.aspx?id=2147512114",
      "year": 2019
    },
    {
      "address": "2360 Sunbury Rd. Columbus, OH 43219",
      "coord_x": 40.0189705,
      "coord_y": -82.9332233,
      "count": 90,
      "date": "10/7/2019",
      "incident": "190850417",
      "source": "https://www.columbus.gov/WorkArea/DownloadAsset.aspx?id=2147512009",
      "year": 2019
    },
    {
      "address": "2477 E. Dublin-Granville Rd. Columbus, OH 43229",
      "coord_x": 40.0837867,
      "coord_y": -82.9525293,
      "count": 91,
      "date": "10/6/2019",
      "incident": "190848554",
      "source": "https://www.columbus.gov/WorkArea/DownloadAsset.aspx?id=2147512197",
      "year": 2019
    },
    {
      "address": "3535 Olentangy River Rd. Columbus, OH 43214",
      "coord_x": 40.0306088,
      "coord_y": -83.03429179999999,
      "count": 92,
      "date": "11/12/2019",
      "incident": "190954512",
      "source": "https://www.columbus.gov/WorkArea/DownloadAsset.aspx?id=2147512576",
      "year": 2019
    },
    {
      "address": "1464 Cordell Ave. Columbus, OH 43211",
      "coord_x": 40.0117176,
      "coord_y": -82.97033880000001,
      "count": 93,
      "date": "11/7/2019",
      "incident": "190387665",
      "source": "https://www.columbus.gov/WorkArea/DownloadAsset.aspx?id=2147512536",
      "year": 2019
    },
    {
      "address": "88 Haldy Ave. Columbus, OH 43204",
      "coord_x": 39.956608,
      "coord_y": -83.0793772,
      "count": 94,
      "date": "11/5/2019",
      "incident": "183021164",
      "source": "https://www.columbus.gov/WorkArea/DownloadAsset.aspx?id=2147512355",
      "year": 2019
    }
  ],
  "overview": {
    "id": 1,
    "sum": 94
  },
  "profile": {
    "name": "typicode"
  }
}
